package/__init__.py
package/__main__.py
basic_python_package_fb-1.0.0.dist-info/METADATA
basic_python_package_fb-1.0.0.dist-info/WHEEL
basic_python_package_fb-1.0.0.dist-info/entry_points.txt
basic_python_package_fb-1.0.0.dist-info/top_level.txt
basic_python_package_fb-1.0.0.dist-info/RECORD
