Metadata-Version: 2.1
Name: basic-python-package-fb
Version: 1.0.0
Summary: UNKNOWN
Home-page: UNKNOWN
Author: UNKNOWN
Author-email: UNKNOWN
License: UNKNOWN
Platform: UNKNOWN
Requires-Dist: django-socio-grpc
